LICENSE
MANIFEST.in
README.rst
setup.py
django_modelfeedback.egg-info/PKG-INFO
django_modelfeedback.egg-info/SOURCES.txt
django_modelfeedback.egg-info/dependency_links.txt
django_modelfeedback.egg-info/top_level.txt
docs/index.txt
modelfeedback/__init__.py
modelfeedback/admin.py
modelfeedback/forms.py
modelfeedback/models.py
modelfeedback/urls.py
modelfeedback/views.py
modelfeedback/templates/modelfeedback/feedback_detail.html
modelfeedback/templates/modelfeedback/feedback_form.html