Metadata-Version: 1.0
Name: django-modelfeedback
Version: 0.1.2
Summary: Adds support for receive feedback to django models using Likert scale.
Home-page: https://github.com/yokomizor/django-modelfeedback
Author: Rogério da Silva Yokomizo
Author-email: me@ro.ger.io
License: MIT License
Platform: UNKNOWN
Classifier: Environment :: Web Environment
Classifier: Framework :: Django
Classifier: Intended Audience :: Developers
Classifier: License :: OSI Approved :: MIT License
Classifier: Operating System :: OS Independent
Classifier: Programming Language :: Python
Classifier: Programming Language :: Python :: 2
Classifier: Programming Language :: Python :: 2.7
Classifier: Topic :: Internet :: WWW/HTTP
Classifier: Topic :: Internet :: WWW/HTTP :: Dynamic Content
